{
  "_class": "shapeGroup",
  "clippingMaskMode": 0,
  "do_objectID": "4C11CEC4-C639-441F-A599-73C8448167A9",
  "exportOptions": {
    "_class": "exportOptions",
    "exportFormats": [
    ],
    "includedLayerIds": [
    ],
    "layerOptions": 0,
    "shouldTrim": false
  },
  "frame": {
    "_class": "rect",
    "constrainProportions": false,
    "height": 2.797923997702867,
    "width": 831,
    "x": 0,
    "y": 166.1609989649491
  },
  "hasClickThrough": false,
  "hasClippingMask": false,
  "isFlippedHorizontal": false,
  "isFlippedVertical": false,
  "isLocked": false,
  "isVisible": true,
  "layerListExpandedType": 0,
  "layers": [
    {
      "class": "shapePath",
      "id": "28073C4D-D7C0-4175-8B21-458952F811F2"
    }
  ],
  "name": "Line Copy 14",
  "nameIsFixed": false,
  "resizingConstraint": 63,
  "resizingType": 0,
  "rotation": 0,
  "shouldBreakMaskChain": false,
  "style": {
    "sharedObjectID": "4347BE76-C4C1-411E-8B81-9C472F6C5A9F"
  },
  "windingRule": 1
}