{
  "_class": "group",
  "do_objectID": "03C70460-A02B-43DC-9D88-E98F4E3E6018",
  "exportOptions": {
    "_class": "exportOptions",
    "exportFormats": [
    ],
    "includedLayerIds": [
    ],
    "layerOptions": 0,
    "shouldTrim": false
  },
  "frame": {
    "_class": "rect",
    "constrainProportions": false,
    "height": 226,
    "width": 831,
    "x": 12,
    "y": 0.5436526394090606
  },
  "hasClickThrough": false,
  "isFlippedHorizontal": false,
  "isFlippedVertical": true,
  "isLocked": false,
  "isVisible": true,
  "layerListExpandedType": 0,
  "layers": [
    {
      "class": "shapeGroup",
      "id": "CBBC8949-DAE6-4B84-B497-F691E9E63A99"
    },
    {
      "class": "shapeGroup",
      "id": "6CE0653E-EA9C-44CF-BA31-73ED3F5F48DF"
    },
    {
      "class": "shapeGroup",
      "id": "EA20667D-CFFC-46A0-8503-17FD57531AC6"
    },
    {
      "class": "shapeGroup",
      "id": "EDE13FB2-78C7-4A2F-847E-A4A0B3E9E206"
    },
    {
      "class": "shapeGroup",
      "id": "9A778428-56A3-4EB1-A55E-89AE347B7E25"
    },
    {
      "class": "shapeGroup",
      "id": "620E0E62-8176-4257-B8C3-A91D4D8D37C5"
    },
    {
      "class": "shapeGroup",
      "id": "5E131827-1DB4-4B32-8538-C3C48C0427B0"
    },
    {
      "class": "shapeGroup",
      "id": "AC1D8A6B-9689-4AAA-9B37-DEEB5ED611B9"
    },
    {
      "class": "shapeGroup",
      "id": "872659E3-2EA2-4E39-A69B-87ABEAF246AA"
    },
    {
      "class": "shapeGroup",
      "id": "C177D264-7EC6-4264-B4A9-C81632D81BF5"
    },
    {
      "class": "shapeGroup",
      "id": "074B7F4A-D981-4460-BBF6-E6BD7C020850"
    },
    {
      "class": "shapeGroup",
      "id": "02679383-FDCB-4657-8BA9-C9C53B56D268"
    },
    {
      "class": "shapeGroup",
      "id": "06CFCCA9-A0F5-4459-BBD7-580135A38CBE"
    },
    {
      "class": "shapeGroup",
      "id": "368F74EE-58C4-4C69-891E-22FF36946399"
    },
    {
      "class": "shapeGroup",
      "id": "59F1A290-803A-493E-BC27-F751F1AFE063"
    }
  ],
  "name": "horiz",
  "nameIsFixed": true,
  "resizingConstraint": 63,
  "resizingType": 0,
  "rotation": 0,
  "shouldBreakMaskChain": false,
  "style": {
    "_class": "style",
    "endDecorationType": 0,
    "miterLimit": 10,
    "startDecorationType": 0
  }
}