{
  "_class": "page",
  "do_objectID": "FCFFE929-8D28-468D-A9FC-BA6D9C8CE94B",
  "exportOptions": {
    "_class": "exportOptions",
    "exportFormats": [
    ],
    "includedLayerIds": [
    ],
    "layerOptions": 0,
    "shouldTrim": false
  },
  "frame": {
    "_class": "rect",
    "constrainProportions": false,
    "height": 300,
    "width": 300,
    "x": 0,
    "y": 0
  },
  "hasClickThrough": true,
  "horizontalRulerData": {
    "_class": "rulerData",
    "base": -548,
    "guides": [
    ]
  },
  "includeInCloudUpload": true,
  "isFlippedHorizontal": false,
  "isFlippedVertical": false,
  "isLocked": false,
  "isVisible": true,
  "layerListExpandedType": 0,
  "layers": [
    {
      "class": "artboard",
      "id": "E43C6899-956D-4F61-9A5F-382D1AC9D01F"
    },
    {
      "class": "artboard",
      "id": "895F02F0-1038-4B49-B5F4-84628F4D4AD9"
    },
    {
      "class": "artboard",
      "id": "C2BDF44F-759E-4CEF-86EC-63CF18181BFE"
    },
    {
      "class": "artboard",
      "id": "5AEC1AFC-0865-4390-B9B7-7CC0413589C6"
    },
    {
      "class": "artboard",
      "id": "9CAD9517-0DE8-4C24-897C-1C58F3FE90D1"
    },
    {
      "class": "artboard",
      "id": "538A0733-2052-4AC1-931F-0115DE64AA9C"
    }
  ],
  "name": "UI",
  "nameIsFixed": true,
  "resizingConstraint": 63,
  "resizingType": 0,
  "rotation": 0,
  "shouldBreakMaskChain": false,
  "style": {
    "_class": "style",
    "endDecorationType": 0,
    "miterLimit": 10,
    "startDecorationType": 0
  },
  "verticalRulerData": {
    "_class": "rulerData",
    "base": -394,
    "guides": [
    ]
  }
}